Metadata-Version: 1.1
Name: dmstudio
Version: 0.0.3
Summary: Python module for Datamine Studio scripting
Home-page: https://github.com/seanhoran/dmstudio
Author: Sean Horan
Author-email: sean.horan@rpacan.com
License: MIT
Download-URL: https://github.com/seanhoran/dmstudio/archive/0.0.3.tar.gz
Platform: UNKNOWN
